Metadata-Version: 2.1
Name: retico-hftranslate
Version: 0.1.1
Summary: Local translation module based on the hugging face transformer
Home-page: https://github.com/retico-team/retico-hftranslate
Download-URL: https://github.com/retico-team/retico-hftranslate
Author: Thilo Michael
Author-email: uhlomuhlo@gmail.com
Keywords: retico,framework,incremental,dialogue,dialog
Classifier: Development Status :: 2 - Pre-Alpha
Classifier: Programming Language :: Python :: 3
Classifier: License :: OSI Approved :: Apache Software License
Requires-Python: >=3.6, <4
License-File: LICENSE
